crawler_tools/__init__.py
crawler_tools/Proxypool/__init__.py
crawler_tools/Proxypool/get_proxy.py
crawler_tools/Proxypool/proxy_schedule.py
crawler_tools/Proxypool/proxy_pool_cui/__init__.py
crawler_tools/Proxypool/proxy_pool_cui/py实例测试.py
crawler_tools/Proxypool/proxy_pool_cui/run.py
crawler_tools/Proxypool/proxy_pool_cui/examples/__init__.py
crawler_tools/Proxypool/proxy_pool_cui/examples/usage.py
crawler_tools/Proxypool/proxy_pool_cui/proxypool/__init__.py
crawler_tools/Proxypool/proxy_pool_cui/proxypool/free_daili（测试写入）.py
crawler_tools/Proxypool/proxy_pool_cui/proxypool/scheduler.py
crawler_tools/Proxypool/proxy_pool_cui/proxypool/setting.py
crawler_tools/Proxypool/proxy_pool_cui/proxypool/crawlers/__init__.py
crawler_tools/Proxypool/proxy_pool_cui/proxypool/crawlers/base.py
crawler_tools/Proxypool/proxy_pool_cui/proxypool/crawlers/private/__init__.py
crawler_tools/Proxypool/proxy_pool_cui/proxypool/crawlers/private/xsdaili.py
crawler_tools/Proxypool/proxy_pool_cui/proxypool/crawlers/public/__init__.py
crawler_tools/Proxypool/proxy_pool_cui/proxypool/crawlers/public/daili66.py
crawler_tools/Proxypool/proxy_pool_cui/proxypool/crawlers/public/ip3366.py
crawler_tools/Proxypool/proxy_pool_cui/proxypool/crawlers/public/iphai.py
crawler_tools/Proxypool/proxy_pool_cui/proxypool/crawlers/public/kuaidaili.py
crawler_tools/Proxypool/proxy_pool_cui/proxypool/exceptions/__init__.py
crawler_tools/Proxypool/proxy_pool_cui/proxypool/exceptions/empty.py
crawler_tools/Proxypool/proxy_pool_cui/proxypool/processors/__init__.py
crawler_tools/Proxypool/proxy_pool_cui/proxypool/processors/getter.py
crawler_tools/Proxypool/proxy_pool_cui/proxypool/processors/server.py
crawler_tools/Proxypool/proxy_pool_cui/proxypool/processors/tester.py
crawler_tools/Proxypool/proxy_pool_cui/proxypool/schemas/__init__.py
crawler_tools/Proxypool/proxy_pool_cui/proxypool/schemas/proxy.py
crawler_tools/Proxypool/proxy_pool_cui/proxypool/storages/__init__.py
crawler_tools-0.0.3.dist-info/METADATA
crawler_tools-0.0.3.dist-info/WHEEL
crawler_tools-0.0.3.dist-info/top_level.txt
crawler_tools-0.0.3.dist-info/RECORD
