Metadata-Version: 2.1
Name: crawler-tools
Version: 0.0.3
Summary: 爬虫工具
Home-page: UNKNOWN
Author: cw
Author-email: 1063117365@qq.com
License: GPL Licence
Keywords: crawler,tools,proxy,cookies,user-agent
Platform: any
Requires-Python: >=3.5.*
Requires-Dist: selenium
Requires-Dist: requests
Requires-Dist: APScheduler
Requires-Dist: werkzeug (==0.15.3)
Requires-Dist: Flask
Requires-Dist: lxml
Requires-Dist: PyExecJS
Requires-Dist: click
Requires-Dist: gunicorn (==19.9.0)
Requires-Dist: redis
Requires-Dist: environs (==7.2.0)
Requires-Dist: attrs
Requires-Dist: retrying
Requires-Dist: aiohttp (==3.6.2)
Requires-Dist: loguru (==0.3.2)
Requires-Dist: pyquery
Requires-Dist: supervisor
